finn/analysis/base.py
finn/analysis/topology.py
finn/core/data_layout.py
finn/core/datatype.py
finn/core/execute_custom_node.py
finn/core/modelwrapper.py
finn/core/onnx_exec.py
finn/core/remote_exec.py
finn/core/rtlsim_exec.py
finn/core/throughput_test.py
finn/custom_op/base.py
finn/custom_op/registry.py
finn/custom_op/general/__init__.py
finn/custom_op/general/debugmarker.py
finn/custom_op/general/im2col.py
finn/custom_op/general/maxpoolnhwc.py
finn/custom_op/general/multithreshold.py
finn/custom_op/general/quantavgpool2d.py
finn/custom_op/general/streamingdataflowpartition.py
finn/custom_op/general/xnorpopcount.py
finn/data/__init__.py
finn/data/onnx/mnist-conv/README.md
finn/data/onnx/mnist-conv/model.onnx
finn/data/onnx/mnist-conv/test_data_set_0/input_0.pb
finn/data/onnx/mnist-conv/test_data_set_0/output_0.pb
finn/data/verilog/myadd/myadd_myadd.v
finn/data/verilog/myadd/myadd_myadd_control_s_axi.v
finn/transformation/base.py
finn/transformation/batchnorm_to_affine.py
finn/transformation/bipolar_to_xnor.py
finn/transformation/change_datalayout.py
finn/transformation/double_to_single_float.py
finn/transformation/fold_constants.py
finn/transformation/general.py
finn/transformation/infer_data_layouts.py
finn/transformation/infer_datatypes.py
finn/transformation/infer_shapes.py
finn/transformation/insert_topk.py
finn/transformation/lower_convs_to_matmul.py
finn/transformation/merge_onnx_models.py
finn/util/basic.py
finn/util/data_packing.py
finn/util/fpgadataflow.py
finn/util/onnx.py
finn/util/pyverilator.py
finn_base-0.0.1a2.dist-info/METADATA
finn_base-0.0.1a2.dist-info/RECORD
finn_base-0.0.1a2.dist-info/WHEEL
finn_base-0.0.1a2.dist-info/top_level.txt
