Metadata-Version: 2.1
Name: finn-base
Version: 0.0.1a2
Summary: Components for ONNX graph manipulation and custom execution
Home-page: https://xilinx.github.io/finn/
Author: Yaman Umuroglu
Author-email: yamanu@xilinx.com
License: new-bsd
Project-URL: Documentation, https://finn-base.readthedocs.io/
Platform: Linux
Classifier: Development Status :: 4 - Beta
Classifier: Programming Language :: Python
Classifier: Operating System :: POSIX :: Linux
Provides-Extra: pyverilator
Provides-Extra: docs
Provides-Extra: onnx
Provides-Extra: testing
Requires-Dist: bitstring (>=3.1.7)
Requires-Dist: numpy (>=1.19.2)
Provides-Extra: docs
Requires-Dist: sphinx (>=3.2.1); extra == 'docs'
Requires-Dist: sphinx-rtd-theme (>=0.5.0); extra == 'docs'
Provides-Extra: onnx
Requires-Dist: onnx (==1.7.0); extra == 'onnx'
Requires-Dist: onnxruntime (==1.4.0); extra == 'onnx'
Requires-Dist: toposort (>=1.5.0); extra == 'onnx'
Provides-Extra: pyverilator
Requires-Dist: pyverilator; extra == 'pyverilator'
Provides-Extra: testing
Requires-Dist: pytest; extra == 'testing'
Requires-Dist: pytest-cov; extra == 'testing'
